bibiflags/__init__.py
bibiflags/bibiflags.py
bibiflags/bibiflags.yaml
bibiflags/test_bibiflags.yaml
examples/config.py
examples/config.yaml
examples/initial.py
examples/initial.yaml
examples/main.py
examples/main.yaml
examples/prog.py
examples/prog.yaml
bibiflags-0.1.5.dist-info/LICENSE
bibiflags-0.1.5.dist-info/METADATA
bibiflags-0.1.5.dist-info/WHEEL
bibiflags-0.1.5.dist-info/top_level.txt
bibiflags-0.1.5.dist-info/RECORD
