Metadata-Version: 2.1
Name: bibiflags
Version: 0.1.5
Summary: Import YAML configs into Arguments for Python
Author-email: Chunqi SHI <chunqishi@gmail.com>
License: MIT
Project-URL: Homepage, https://github.com/bibiparrot/bibiflags
Project-URL: Issues, https://github.com/bibiparrot/bibiflags/issues
Classifier: Programming Language :: Python :: 3
Classifier: License :: OSI Approved :: MIT License
Classifier: Operating System :: OS Independent
Requires-Python: >=3.8
License-File: LICENSE
Requires-Dist: PyYAML >=6.0.1
